LICENSE
MANIFEST.in
README.md
march.py
setup.py
march.egg-info/PKG-INFO
march.egg-info/SOURCES.txt
march.egg-info/dependency_links.txt
march.egg-info/entry_points.txt
march.egg-info/top_level.txt