Metadata-Version: 2.1
Name: march
Version: 0.1
Summary: Multi-Arch Wrapper Script
Home-page: https://github.com/frispete/march
Author: Hans-Peter Jansen
Author-email: hpj@urpla.net
License: GNU GPL v2 - see http://www.gnu.org/licenses/gpl2.txt for details
Classifier: Development Status :: 4 - Beta
Classifier: Intended Audience :: System Administrators
Classifier: License :: OSI Approved :: GNU General Public License v2 (GPLv2)
Classifier: Operating System :: POSIX
Classifier: Operating System :: POSIX :: Linux
Classifier: Programming Language :: Python :: 3.6
Classifier: Programming Language :: Python :: 3.7
Classifier: Programming Language :: Python :: 3.8
Classifier: Programming Language :: Python :: 3.9
Classifier: Programming Language :: Python :: 3.10
Requires-Python: >=3
License-File: LICENSE
